magzdb/__init__.py
magzdb/cli.py
magzdb/downloader.py
magzdb/magzdb.py
magzdb/version.py
magzdb-1.2.0.dist-info/LICENSE
magzdb-1.2.0.dist-info/METADATA
magzdb-1.2.0.dist-info/WHEEL
magzdb-1.2.0.dist-info/entry_points.txt
magzdb-1.2.0.dist-info/top_level.txt
magzdb-1.2.0.dist-info/RECORD
