Metadata-Version: 2.1
Name: magzdb
Version: 1.2.0
Summary: Magzdb.org Downloader
Home-page: https://github.com/skyme5/magzdb
Author: Aakash Gajjar
Author-email: skyqutip@gmail.com
License: MIT license
Keywords: magzdb
Platform: UNKNOWN
Classifier: Development Status :: 5 - Production/Stable
Classifier: Intended Audience :: End Users/Desktop 
Classifier: License :: OSI Approved :: MIT License
Classifier: Natural Language :: English
Classifier: Programming Language :: Python :: 3
Classifier: Programming Language :: Python :: 3.6
Classifier: Programming Language :: Python :: 3.7
Classifier: Programming Language :: Python :: 3.8
Classifier: Programming Language :: Python :: 3.9
Classifier: Programming Language :: Python :: 3.10
Requires-Python: >=3.5
Requires-Dist: loguru (>=0.5.3)
Requires-Dist: requests (>=2.24.0)
